{
"skeleton": { "hash": "7p1kimOPCjs", "spine": "4.2.33", "images": "../Mage/Infernal Meteor Rain/0/", "audio": "../Resource/Mage/0124/" },
"bones": [
	{ "name": "root", "scaleX": 1.9413, "scaleY": 1.9413 },
	{ "name": "bone", "parent": "root" },
	{ "name": "qiliu", "parent": "bone" },
	{ "name": "quan", "parent": "bone" },
	{ "name": "quan2", "parent": "bone" },
	{ "name": "quan3", "parent": "bone" },
	{ "name": "rao", "parent": "bone", "scaleX": -1.5, "scaleY": 1.5 },
	{ "name": "rao2", "parent": "bone", "scaleX": -1.5, "scaleY": 1.5 },
	{ "name": "rao3", "parent": "bone", "scaleX": -1.5, "scaleY": 1.5 },
	{ "name": "yunshi", "parent": "bone" },
	{ "name": "2005211_atk1_impact_00", "parent": "root", "scaleX": 1.2765, "scaleY": 1.2765 }
],
"slots": [
	{ "name": "texiao-skill1-yunshi-yhushi_0000", "bone": "yunshi" },
	{ "name": "quan", "bone": "quan", "blend": "additive" },
	{ "name": "quan2", "bone": "quan2", "blend": "additive" },
	{ "name": "quan3", "bone": "quan3", "blend": "additive" },
	{ "name": "qiliu", "bone": "qiliu", "blend": "additive" },
	{ "name": "rao", "bone": "rao" },
	{ "name": "rao2", "bone": "rao2" },
	{ "name": "rao3", "bone": "rao3" },
	{ "name": "2005211_atk1_impact_00", "bone": "2005211_atk1_impact_00" },
	{ "name": "00000", "bone": "yunshi" }
],
"skins": [
	{
		"name": "default",
		"attachments": {
			"00000": {
				"00000": { "width": 576, "height": 576 },
				"00002": { "width": 576, "height": 576 },
				"00004": { "width": 576, "height": 576 }
			},
			"2005211_atk1_impact_00": {
				"skill1/2005211_atk1_impact_00": { "y": 84.34, "width": 449, "height": 321 },
				"skill1/2005211_atk1_impact_01": { "y": 84.34, "width": 449, "height": 321 },
				"skill1/2005211_atk1_impact_02": { "y": 84.34, "width": 449, "height": 321 },
				"skill1/2005211_atk1_impact_03": { "y": 84.34, "width": 449, "height": 321 },
				"skill1/2005211_atk1_impact_04": { "y": 84.34, "width": 449, "height": 321 },
				"skill1/2005211_atk1_impact_05": { "y": 84.34, "width": 449, "height": 321 },
				"skill1/2005211_atk1_impact_06": { "y": 84.34, "width": 449, "height": 321 },
				"skill1/2005211_atk1_impact_07": { "y": 84.34, "width": 449, "height": 321 },
				"skill1/2005211_atk1_impact_08": { "y": 84.34, "width": 449, "height": 321 },
				"skill1/2005211_atk1_impact_09": { "y": 84.34, "width": 449, "height": 321 },
				"skill1/2005211_atk1_impact_10": { "y": 84.34, "width": 449, "height": 321 },
				"skill1/2005211_atk1_impact_11": { "y": 84.34, "width": 449, "height": 321 },
				"skill1/2005211_atk1_impact_12": { "y": 84.34, "width": 449, "height": 321 },
				"skill1/2005211_atk1_impact_13": { "y": 84.34, "width": 449, "height": 321 },
				"skill1/2005211_atk1_impact_14": { "y": 84.34, "width": 449, "height": 321 }
			},
			"qiliu": {
				"skill1/qiliu/1_00000": { "width": 173, "height": 183 },
				"skill1/qiliu/1_00002": { "width": 173, "height": 183 },
				"skill1/qiliu/1_00004": { "width": 173, "height": 183 },
				"skill1/qiliu/1_00006": { "width": 173, "height": 183 },
				"skill1/qiliu/1_00008": { "width": 173, "height": 183 },
				"skill1/qiliu/1_00010": { "width": 173, "height": 183 },
				"skill1/qiliu/1_00012": { "width": 173, "height": 183 },
				"skill1/qiliu/1_00014": { "width": 173, "height": 183 },
				"skill1/qiliu/1_00016": { "width": 173, "height": 183 },
				"skill1/qiliu/1_00018": { "width": 173, "height": 183 }
			},
			"quan": {
				"skill1/quan_00048": { "width": 88, "height": 183 }
			},
			"quan2": {
				"skill1/quan_00048": { "width": 88, "height": 183 }
			},
			"quan3": {
				"skill1/quan_00048": { "width": 88, "height": 183 }
			},
			"rao": {
				"skill1/quan/1_00006": { "width": 239, "height": 109 },
				"skill1/quan/1_00009": { "width": 239, "height": 109 },
				"skill1/quan/1_00012": { "width": 239, "height": 109 },
				"skill1/quan/1_00018": { "width": 239, "height": 109 },
				"skill1/quan/1_00024": { "width": 239, "height": 109 },
				"skill1/quan/1_00030": { "width": 239, "height": 109 },
				"skill1/quan/1_00036": { "width": 239, "height": 109 },
				"skill1/quan/1_00048": { "width": 239, "height": 109 }
			},
			"rao2": {
				"skill1/quan/1_00006": { "width": 239, "height": 109 },
				"skill1/quan/1_00009": { "width": 239, "height": 109 },
				"skill1/quan/1_00012": { "width": 239, "height": 109 },
				"skill1/quan/1_00018": { "width": 239, "height": 109 },
				"skill1/quan/1_00024": { "width": 239, "height": 109 },
				"skill1/quan/1_00030": { "width": 239, "height": 109 },
				"skill1/quan/1_00036": { "width": 239, "height": 109 },
				"skill1/quan/1_00048": { "width": 239, "height": 109 }
			},
			"rao3": {
				"skill1/quan/1_00006": { "width": 239, "height": 109 },
				"skill1/quan/1_00009": { "width": 239, "height": 109 },
				"skill1/quan/1_00012": { "width": 239, "height": 109 },
				"skill1/quan/1_00018": { "width": 239, "height": 109 },
				"skill1/quan/1_00024": { "width": 239, "height": 109 },
				"skill1/quan/1_00030": { "width": 239, "height": 109 },
				"skill1/quan/1_00036": { "width": 239, "height": 109 },
				"skill1/quan/1_00048": { "width": 239, "height": 109 }
			},
			"texiao-skill1-yunshi-yhushi_0000": {
				"skill1/yunshi/1_00000": { "width": 104, "height": 147 },
				"skill1/yunshi/1_00002": { "width": 104, "height": 147 },
				"skill1/yunshi/1_00004": { "width": 104, "height": 147 },
				"skill1/yunshi/1_00006": { "width": 104, "height": 147 },
				"skill1/yunshi/1_00008": { "width": 104, "height": 147 },
				"skill1/yunshi/1_00010": { "width": 104, "height": 147 },
				"skill1/yunshi/1_00012": { "width": 104, "height": 147 },
				"skill1/yunshi/1_00014": { "width": 104, "height": 147 },
				"skill1/yunshi/1_00016": { "width": 104, "height": 147 },
				"skill1/yunshi/1_00018": { "width": 104, "height": 147 }
			}
		}
	}
],
"events": {
	"hit": {}
},
"animations": {
	"animation": {
		"slots": {
			"00000": {
				"attachment": [
					{ "name": "00000" },
					{ "time": 0.0667, "name": "00002" },
					{ "time": 0.1333, "name": "00004" },
					{ "time": 0.2, "name": "00000" },
					{ "time": 0.2667, "name": "00002" },
					{ "time": 0.3333, "name": "00004" },
					{ "time": 0.4, "name": "00000" },
					{ "time": 0.4667, "name": "00002" },
					{ "time": 0.5333, "name": "00004" },
					{ "time": 0.6, "name": "00000" },
					{ "time": 0.6667, "name": "00002" },
					{ "time": 0.7333, "name": "00004" },
					{ "time": 0.8, "name": "00000" },
					{ "time": 0.8667, "name": "00002" },
					{ "time": 0.9333, "name": "00004" },
					{ "time": 1, "name": "00000" },
					{ "time": 1.0667, "name": "00002" },
					{ "time": 1.1333, "name": "00004" },
					{ "time": 1.2, "name": "00000" },
					{ "time": 1.2667, "name": "00002" },
					{ "time": 1.3333, "name": "00004" },
					{ "time": 1.4, "name": "00000" },
					{ "time": 1.4667, "name": "00002" },
					{ "time": 1.5333, "name": "00004" },
					{ "time": 1.6, "name": "00000" },
					{ "time": 1.6667, "name": "00002" },
					{ "time": 1.7333, "name": "00004" },
					{ "time": 1.8 }
				]
			},
			"2005211_atk1_impact_00": {
				"attachment": [
					{ "time": 1.8, "name": "skill1/2005211_atk1_impact_00" },
					{ "time": 1.8333, "name": "skill1/2005211_atk1_impact_01" },
					{ "time": 1.8667, "name": "skill1/2005211_atk1_impact_02" },
					{ "time": 1.9, "name": "skill1/2005211_atk1_impact_03" },
					{ "time": 1.9333, "name": "skill1/2005211_atk1_impact_04" },
					{ "time": 1.9667, "name": "skill1/2005211_atk1_impact_05" },
					{ "time": 2, "name": "skill1/2005211_atk1_impact_06" },
					{ "time": 2.0333, "name": "skill1/2005211_atk1_impact_07" },
					{ "time": 2.0667, "name": "skill1/2005211_atk1_impact_08" },
					{ "time": 2.1, "name": "skill1/2005211_atk1_impact_09" },
					{ "time": 2.1333, "name": "skill1/2005211_atk1_impact_10" },
					{ "time": 2.1667, "name": "skill1/2005211_atk1_impact_11" },
					{ "time": 2.2, "name": "skill1/2005211_atk1_impact_12" },
					{ "time": 2.2333, "name": "skill1/2005211_atk1_impact_13" },
					{ "time": 2.2667, "name": "skill1/2005211_atk1_impact_14" },
					{ "time": 2.3 }
				]
			},
			"qiliu": {
				"rgba": [
					{ "time": 1.3, "color": "ffffffff" },
					{ "time": 1.7333, "color": "ffffff00" }
				],
				"attachment": [
					{ "time": 0.0333, "name": "skill1/qiliu/1_00000" },
					{ "time": 0.1, "name": "skill1/qiliu/1_00002" },
					{ "time": 0.1667, "name": "skill1/qiliu/1_00004" },
					{ "time": 0.2333, "name": "skill1/qiliu/1_00006" },
					{ "time": 0.3, "name": "skill1/qiliu/1_00008" },
					{ "time": 0.3667, "name": "skill1/qiliu/1_00010" },
					{ "time": 0.4333, "name": "skill1/qiliu/1_00012" },
					{ "time": 0.5, "name": "skill1/qiliu/1_00014" },
					{ "time": 0.5667, "name": "skill1/qiliu/1_00016" },
					{ "time": 0.6333, "name": "skill1/qiliu/1_00018" },
					{ "time": 0.7, "name": "skill1/qiliu/1_00000" },
					{ "time": 0.7667, "name": "skill1/qiliu/1_00002" },
					{ "time": 0.8333, "name": "skill1/qiliu/1_00004" },
					{ "time": 0.9, "name": "skill1/qiliu/1_00006" },
					{ "time": 0.9667, "name": "skill1/qiliu/1_00008" },
					{ "time": 1.0333, "name": "skill1/qiliu/1_00010" },
					{ "time": 1.1, "name": "skill1/qiliu/1_00012" },
					{ "time": 1.1667, "name": "skill1/qiliu/1_00014" },
					{ "time": 1.2333, "name": "skill1/qiliu/1_00016" },
					{ "time": 1.3, "name": "skill1/qiliu/1_00018" },
					{ "time": 1.3667, "name": "skill1/qiliu/1_00000" },
					{ "time": 1.4333, "name": "skill1/qiliu/1_00002" },
					{ "time": 1.5, "name": "skill1/qiliu/1_00004" },
					{ "time": 1.5667, "name": "skill1/qiliu/1_00006" },
					{ "time": 1.6333, "name": "skill1/qiliu/1_00008" },
					{ "time": 1.7, "name": "skill1/qiliu/1_00010" }
				]
			},
			"quan": {
				"rgba": [
					{ "time": 0.1, "color": "ffffffff" },
					{ "time": 1.8, "color": "ff000000" }
				],
				"attachment": [
					{ "name": "skill1/quan_00048" }
				]
			},
			"quan2": {
				"rgba": [
					{ "time": 0.7667, "color": "ffffffff" },
					{ "time": 1.8, "color": "ff000000" }
				],
				"attachment": [
					{ "time": 0.6667, "name": "skill1/quan_00048" }
				]
			},
			"quan3": {
				"rgba": [
					{ "time": 1.7, "color": "ffffffff" },
					{ "time": 1.8, "color": "ff000000" }
				],
				"attachment": [
					{ "time": 1.6, "name": "skill1/quan_00048" }
				]
			},
			"rao": {
				"rgba": [
					{ "time": 0.0333, "color": "ffffff8a", "curve": "stepped" },
					{ "time": 0.1333, "color": "ffffff8a" },
					{ "time": 0.5667, "color": "ffffff00" }
				],
				"attachment": [
					{ "time": 0.0333, "name": "skill1/quan/1_00006" },
					{ "time": 0.1, "name": "skill1/quan/1_00009" },
					{ "time": 0.1667, "name": "skill1/quan/1_00012" },
					{ "time": 0.2333, "name": "skill1/quan/1_00018" },
					{ "time": 0.3, "name": "skill1/quan/1_00024" },
					{ "time": 0.3667, "name": "skill1/quan/1_00030" },
					{ "time": 0.4333, "name": "skill1/quan/1_00036" },
					{ "time": 0.5, "name": "skill1/quan/1_00048" },
					{ "time": 0.5667 }
				]
			},
			"rao2": {
				"rgba": [
					{ "time": 0.0667, "color": "8800009c", "curve": "stepped" },
					{ "time": 0.1, "color": "8800009c" },
					{ "time": 0.2667, "color": "88000000" }
				],
				"attachment": [
					{ "time": 0.0667, "name": "skill1/quan/1_00006" },
					{ "time": 0.1, "name": "skill1/quan/1_00009" },
					{ "time": 0.1333, "name": "skill1/quan/1_00012" },
					{ "time": 0.1667, "name": "skill1/quan/1_00018" },
					{ "time": 0.2, "name": "skill1/quan/1_00024" },
					{ "time": 0.2333, "name": "skill1/quan/1_00030" },
					{ "time": 0.2667, "name": "skill1/quan/1_00036" },
					{ "time": 0.3, "name": "skill1/quan/1_00048" },
					{ "time": 0.3333 }
				]
			},
			"rao3": {
				"rgba": [
					{ "time": 0.2, "color": "8800009c", "curve": "stepped" },
					{ "time": 0.2333, "color": "8800009c" },
					{ "time": 0.4, "color": "88000000" }
				],
				"attachment": [
					{ "time": 0.2, "name": "skill1/quan/1_00012" },
					{ "time": 0.2333, "name": "skill1/quan/1_00018" },
					{ "time": 0.2667, "name": "skill1/quan/1_00024" },
					{ "time": 0.3, "name": "skill1/quan/1_00030" },
					{ "time": 0.3333, "name": "skill1/quan/1_00036" },
					{ "time": 0.3667, "name": "skill1/quan/1_00048" },
					{ "time": 0.4 }
				]
			},
			"texiao-skill1-yunshi-yhushi_0000": {
				"attachment": [
					{ "name": "skill1/yunshi/1_00000" },
					{ "time": 0.0667, "name": "skill1/yunshi/1_00002" },
					{ "time": 0.1333, "name": "skill1/yunshi/1_00004" },
					{ "time": 0.2, "name": "skill1/yunshi/1_00006" },
					{ "time": 0.2667, "name": "skill1/yunshi/1_00008" },
					{ "time": 0.3333, "name": "skill1/yunshi/1_00010" },
					{ "time": 0.4, "name": "skill1/yunshi/1_00012" },
					{ "time": 0.4667, "name": "skill1/yunshi/1_00014" },
					{ "time": 0.5333, "name": "skill1/yunshi/1_00016" },
					{ "time": 0.6, "name": "skill1/yunshi/1_00018" },
					{ "time": 0.6667, "name": "skill1/yunshi/1_00000" },
					{ "time": 0.7333, "name": "skill1/yunshi/1_00002" },
					{ "time": 0.8, "name": "skill1/yunshi/1_00004" },
					{ "time": 0.8667, "name": "skill1/yunshi/1_00006" },
					{ "time": 0.9333, "name": "skill1/yunshi/1_00008" },
					{ "time": 1, "name": "skill1/yunshi/1_00010" },
					{ "time": 1.0667, "name": "skill1/yunshi/1_00012" },
					{ "time": 1.1333, "name": "skill1/yunshi/1_00014" },
					{ "time": 1.2, "name": "skill1/yunshi/1_00016" },
					{ "time": 1.2667, "name": "skill1/yunshi/1_00018" },
					{ "time": 1.3333, "name": "skill1/yunshi/1_00000" },
					{ "time": 1.4, "name": "skill1/yunshi/1_00002" },
					{ "time": 1.4667, "name": "skill1/yunshi/1_00004" },
					{ "time": 1.5333, "name": "skill1/yunshi/1_00006" },
					{ "time": 1.6, "name": "skill1/yunshi/1_00008" },
					{ "time": 1.6667, "name": "skill1/yunshi/1_00010" },
					{ "time": 1.7333, "name": "skill1/yunshi/1_00012" },
					{ "time": 1.8 }
				]
			}
		},
		"bones": {
			"qiliu": {
				"rotate": [
					{ "time": 0.0333, "value": -125.71 }
				],
				"translate": [
					{ "time": 0.0333, "x": -9, "y": 257.03 },
					{ "time": 1.7333, "x": 202.91, "y": 93.08 }
				],
				"scale": [
					{ "time": 0.0333, "x": 1.787, "y": 1.787 },
					{ "time": 1.7333, "x": 3.758, "y": 3.758 }
				]
			},
			"quan": {
				"rotate": [
					{ "value": 137.66 }
				],
				"translate": [
					{ "x": 100.27, "y": 192.29 }
				],
				"scale": [
					{ "x": 0.773, "y": 0.773 },
					{ "time": 1.8, "x": 3.012, "y": 3.012 }
				]
			},
			"quan2": {
				"rotate": [
					{ "time": 0.6667, "value": 137.66 }
				],
				"translate": [
					{ "time": 0.6667, "x": 145.59, "y": 151.09 }
				],
				"scale": [
					{ "time": 0.6667, "x": 0.773, "y": 0.773 },
					{ "time": 1.8, "x": 2.052, "y": 2.052 }
				]
			},
			"quan3": {
				"rotate": [
					{ "time": 1.6, "value": 137.66 }
				],
				"translate": [
					{ "time": 1.6, "x": 269.21, "y": 70.05 }
				],
				"scale": [
					{ "time": 1.6, "x": 0.767, "y": 0.767 },
					{ "time": 1.9, "x": 2.052, "y": 2.052 }
				]
			},
			"rao": {
				"rotate": [
					{ "time": 0.0333, "value": -137.92 }
				],
				"translate": [
					{ "time": 0.0333, "x": 83.88, "y": 215.08 }
				],
				"scale": [
					{ "time": 0.0333, "x": -1.667, "y": 1.928 },
					{ "time": 0.1333, "x": -2.113, "y": 2.443 },
					{ "time": 0.5667, "x": -3.207, "y": 3.709 }
				]
			},
			"rao2": {
				"rotate": [
					{ "time": 0.0667, "value": 10.55 }
				],
				"translate": [
					{ "time": 0.0667, "x": 38.16, "y": 246.51 }
				],
				"scale": [
					{ "time": 0.0667, "x": -0.891, "y": -0.628 },
					{ "time": 0.1, "x": -1.453, "y": -1.024 },
					{ "time": 0.2667, "x": -3.454, "y": -2.435 }
				]
			},
			"rao3": {
				"rotate": [
					{ "time": 0.2, "value": -21 }
				],
				"translate": [
					{ "time": 0.2, "x": -44.28, "y": 311.73 }
				],
				"scale": [
					{ "time": 0.2, "x": -0.891, "y": -0.628 },
					{ "time": 0.2333, "x": -2.728, "y": -1.923 },
					{ "time": 0.4, "x": -3.454, "y": -2.435 }
				]
			},
			"yunshi": {
				"rotate": [
					{ "value": 53.4 }
				],
				"translate": [
					{
						"x": -7.93,
						"y": 278.02,
						"curve": [ 0.981, 0.75, 1.596, 218.7, 0.981, 271.39, 1.596, 60.75 ]
					},
					{ "time": 1.8, "x": 344.88, "y": -44.41 }
				],
				"scale": [
					{ "x": 2.34, "y": 2.34 },
					{ "time": 1.8, "x": 2.304, "y": 2.304 }
				]
			},
			"bone": {
				"rotate": [
					{ "value": -13.49 }
				],
				"translate": [
					{ "x": -453.06, "y": 328.39 }
				]
			},
			"2005211_atk1_impact_00": {
				"scale": [
					{ "time": 1.8, "x": 1.772, "y": 1.772 }
				]
			}
		},
		"events": [
			{ "time": 1.8333, "name": "hit" }
		]
	}
}
}