{
"skeleton": {
	"hash": "N+t85YEiKrM",
	"spine": "4.2.33",
	"x": -540,
	"y": -563.29,
	"width": 1080,
	"height": 1920,
	"images": "./images2/",
	"audio": "./audio"
},
"bones": [
	{ "name": "root" },
	{ "name": "VFX", "parent": "root", "scaleX": 0.3942, "scaleY": 0.3942 },
	{ "name": "FX_spin_slash", "parent": "VFX", "x": -1478.39, "y": 10.38 },
	{ "name": "MAIN5", "parent": "FX_spin_slash", "icon": "rotate" },
	{ "name": "MAIN6", "parent": "FX_spin_slash", "icon": "rotate" },
	{ "name": "MAIN7", "parent": "FX_spin_slash", "icon": "rotate" },
	{ "name": "1_00", "parent": "VFX", "scaleX": 6.7652, "scaleY": 6.7652 },
	{ "name": "2_00", "parent": "VFX", "scaleX": 4.96, "scaleY": 4.96 },
	{ "name": "skill-1jiaodiqiliu_00045", "parent": "VFX", "scaleX": 10.9124, "scaleY": 10.9124 }
],
"slots": [
	{ "name": "frame1920x1080", "bone": "root" },
	{ "name": "skill-1jiaodiqiliu_00045", "bone": "skill-1jiaodiqiliu_00045" },
	{ "name": "spin_slash/spin_splash_2", "bone": "MAIN6" },
	{ "name": "spin_slash/spin_splash_1", "bone": "MAIN5" },
	{ "name": "spin_slash/spin_splash_3", "bone": "MAIN7" },
	{ "name": "2_00", "bone": "2_00", "blend": "additive" },
	{ "name": "1_00", "bone": "1_00" }
],
"skins": [
	{
		"name": "default",
		"attachments": {
			"1_00": {
				"VFX/1_00": { "width": 553, "height": 185 },
				"VFX/1_01": { "width": 553, "height": 185 },
				"VFX/1_02": { "width": 553, "height": 185 },
				"VFX/1_03": { "width": 553, "height": 185 },
				"VFX/1_04": { "width": 553, "height": 185 },
				"VFX/1_05": { "width": 553, "height": 185 },
				"VFX/1_06": { "width": 553, "height": 185 },
				"VFX/1_07": { "width": 553, "height": 185 },
				"VFX/1_08": { "width": 553, "height": 185 },
				"VFX/1_09": { "width": 553, "height": 185 },
				"VFX/1_10": { "width": 553, "height": 185 },
				"VFX/1_11": { "width": 553, "height": 185 },
				"VFX/1_12": { "width": 553, "height": 185 }
			},
			"2_00": {
				"VFX/2_00": { "width": 584, "height": 242 },
				"VFX/2_01": { "width": 584, "height": 242 },
				"VFX/2_02": { "width": 584, "height": 242 },
				"VFX/2_03": { "width": 584, "height": 242 },
				"VFX/2_04": { "width": 584, "height": 242 },
				"VFX/2_05": { "width": 584, "height": 242 },
				"VFX/2_06": { "width": 584, "height": 242 },
				"VFX/2_07": { "width": 584, "height": 242 },
				"VFX/2_08": { "width": 584, "height": 242 },
				"VFX/2_09": { "width": 584, "height": 242 },
				"VFX/2_10": { "width": 584, "height": 242 },
				"VFX/2_11": { "width": 584, "height": 242 },
				"VFX/2_12": { "width": 584, "height": 242 },
				"VFX/2_13": { "width": 584, "height": 242 },
				"VFX/2_14": { "width": 584, "height": 242 },
				"VFX/2_15": { "width": 584, "height": 242 }
			},
			"skill-1jiaodiqiliu_00045": {
				"VFX/skill-1jiaodiqiliu_00045": { "width": 191, "height": 81 },
				"VFX/skill-1jiaodiqiliu_00047": { "width": 191, "height": 81 },
				"VFX/skill-1jiaodiqiliu_00049": { "width": 191, "height": 81 },
				"VFX/skill-1jiaodiqiliu_00051": { "width": 191, "height": 81 },
				"VFX/skill-1jiaodiqiliu_00053": { "width": 191, "height": 81 },
				"VFX/skill-1jiaodiqiliu_00055": { "width": 191, "height": 81 },
				"VFX/skill-1jiaodiqiliu_00057": { "width": 191, "height": 81 },
				"VFX/skill-1jiaodiqiliu_00059": { "width": 191, "height": 81 }
			},
			"spin_slash/spin_splash_1": {
				"FX/heavy_slash/heavy_slash_": {
					"scaleX": 1.7066,
					"scaleY": 1.7066,
					"width": 500,
					"height": 500,
					"sequence": { "count": 7, "start": 3 }
				},
				"FX/spin/spin_splash_": {
					"scaleX": 1.7066,
					"scaleY": 1.7066,
					"width": 500,
					"height": 500,
					"sequence": { "count": 8, "start": 0 }
				}
			},
			"spin_slash/spin_splash_2": {
				"FX/spin/dusk_": {
					"scaleX": 1.9271,
					"scaleY": 1.9271,
					"rotation": -116.17,
					"width": 500,
					"height": 500,
					"sequence": { "count": 5 }
				}
			},
			"spin_slash/spin_splash_3": {
				"FX/spin/spark_": {
					"y": 6,
					"scaleX": 1.7543,
					"scaleY": 1.7543,
					"rotation": -116.17,
					"width": 500,
					"height": 500,
					"sequence": { "count": 5, "start": 3 }
				}
			}
		}
	}
],
"events": {
	"hit": {}
},
"animations": {
	"animation": {
		"slots": {
			"1_00": {
				"attachment": [
					{ "name": "VFX/1_00" },
					{ "time": 0.0333, "name": "VFX/1_01" },
					{ "time": 0.0667, "name": "VFX/1_02" },
					{ "time": 0.1, "name": "VFX/1_03" },
					{ "time": 0.1333, "name": "VFX/1_04" },
					{ "time": 0.1667, "name": "VFX/1_05" },
					{ "time": 0.2, "name": "VFX/1_06" },
					{ "time": 0.2333, "name": "VFX/1_07" },
					{ "time": 0.2667, "name": "VFX/1_08" },
					{ "time": 0.3, "name": "VFX/1_09" },
					{ "time": 0.3333, "name": "VFX/1_10" },
					{ "time": 0.3667, "name": "VFX/1_11" },
					{ "time": 0.4, "name": "VFX/1_12" },
					{ "time": 0.4333, "name": "VFX/1_00" },
					{ "time": 0.4667, "name": "VFX/1_01" },
					{ "time": 0.5, "name": "VFX/1_02" },
					{ "time": 0.5333, "name": "VFX/1_03" },
					{ "time": 0.5667, "name": "VFX/1_04" },
					{ "time": 0.6, "name": "VFX/1_05" },
					{ "time": 0.6333, "name": "VFX/1_06" },
					{ "time": 0.6667, "name": "VFX/1_07" },
					{ "time": 0.7, "name": "VFX/1_08" },
					{ "time": 0.7333, "name": "VFX/1_09" },
					{ "time": 0.7667, "name": "VFX/1_10" },
					{ "time": 0.8, "name": "VFX/1_11" },
					{ "time": 0.8333, "name": "VFX/1_12" }
				]
			},
			"2_00": {
				"attachment": [
					{ "name": "VFX/2_00" },
					{ "time": 0.0667, "name": "VFX/2_01" },
					{ "time": 0.1, "name": "VFX/2_02" },
					{ "time": 0.1667, "name": "VFX/2_03" },
					{ "time": 0.2333, "name": "VFX/2_04" },
					{ "time": 0.2667, "name": "VFX/2_05" },
					{ "time": 0.3333, "name": "VFX/2_06" },
					{ "time": 0.3667, "name": "VFX/2_07" },
					{ "time": 0.4333, "name": "VFX/2_08" },
					{ "time": 0.5, "name": "VFX/2_09" },
					{ "time": 0.5333, "name": "VFX/2_10" },
					{ "time": 0.6, "name": "VFX/2_11" },
					{ "time": 0.6667, "name": "VFX/2_12" },
					{ "time": 0.7, "name": "VFX/2_13" },
					{ "time": 0.7667, "name": "VFX/2_14" },
					{ "time": 0.8, "name": "VFX/2_15" }
				]
			},
			"skill-1jiaodiqiliu_00045": {
				"attachment": [
					{ "name": "VFX/skill-1jiaodiqiliu_00045" },
					{ "time": 0.0333, "name": "VFX/skill-1jiaodiqiliu_00047" },
					{ "time": 0.0667, "name": "VFX/skill-1jiaodiqiliu_00049" },
					{ "time": 0.1, "name": "VFX/skill-1jiaodiqiliu_00051" },
					{ "time": 0.1333, "name": "VFX/skill-1jiaodiqiliu_00053" },
					{ "time": 0.1667, "name": "VFX/skill-1jiaodiqiliu_00055" },
					{ "time": 0.2, "name": "VFX/skill-1jiaodiqiliu_00057" },
					{ "time": 0.2333, "name": "VFX/skill-1jiaodiqiliu_00059" },
					{ "time": 0.2667, "name": "VFX/skill-1jiaodiqiliu_00045" },
					{ "time": 0.3, "name": "VFX/skill-1jiaodiqiliu_00047" },
					{ "time": 0.3333, "name": "VFX/skill-1jiaodiqiliu_00049" },
					{ "time": 0.3667, "name": "VFX/skill-1jiaodiqiliu_00051" },
					{ "time": 0.4333, "name": "VFX/skill-1jiaodiqiliu_00053" },
					{ "time": 0.4667, "name": "VFX/skill-1jiaodiqiliu_00055" },
					{ "time": 0.5, "name": "VFX/skill-1jiaodiqiliu_00057" },
					{ "time": 0.5333, "name": "VFX/skill-1jiaodiqiliu_00059" },
					{ "time": 0.5667, "name": "VFX/skill-1jiaodiqiliu_00045" },
					{ "time": 0.6, "name": "VFX/skill-1jiaodiqiliu_00047" },
					{ "time": 0.6333, "name": "VFX/skill-1jiaodiqiliu_00049" },
					{ "time": 0.6667, "name": "VFX/skill-1jiaodiqiliu_00051" },
					{ "time": 0.7, "name": "VFX/skill-1jiaodiqiliu_00053" },
					{ "time": 0.7333, "name": "VFX/skill-1jiaodiqiliu_00055" },
					{ "time": 0.7667, "name": "VFX/skill-1jiaodiqiliu_00057" },
					{ "time": 0.8, "name": "VFX/skill-1jiaodiqiliu_00059" }
				]
			},
			"spin_slash/spin_splash_1": {
				"attachment": [
					{ "name": "FX/spin/spin_splash_" }
				]
			},
			"spin_slash/spin_splash_2": {
				"attachment": [
					{ "name": "FX/spin/dusk_" }
				]
			},
			"spin_slash/spin_splash_3": {
				"attachment": [
					{ "name": "FX/spin/spark_" }
				]
			}
		},
		"bones": {
			"FX_spin_slash": {
				"translate": [
					{ "x": 1481.25, "y": 392.28 }
				],
				"scale": [
					{ "x": 4.31, "y": 1.362 }
				]
			},
			"MAIN5": {
				"rotate": [
					{},
					{ "time": 0.4, "value": 913.93 },
					{ "time": 0.4333 },
					{ "time": 0.8333, "value": 913.93 }
				]
			},
			"MAIN6": {
				"rotate": [
					{ "value": -133.95 },
					{ "time": 0.1, "value": 77 },
					{ "time": 0.4, "value": 378.92 },
					{ "time": 0.4333, "value": -133.95 },
					{ "time": 0.5333, "value": 77 },
					{ "time": 0.8333, "value": 378.92 }
				],
				"translate": [
					{ "y": -70.91 }
				],
				"scale": [
					{ "x": 0.882, "y": 0.882 },
					{ "time": 0.1667, "x": 1.098, "y": 1.098, "curve": "stepped" },
					{ "time": 0.2, "x": 0.882, "y": 0.882 },
					{ "time": 0.4, "x": 1.098, "y": 1.098 },
					{ "time": 0.4333, "x": 0.882, "y": 0.882 },
					{ "time": 0.6, "x": 1.098, "y": 1.098, "curve": "stepped" },
					{ "time": 0.6333, "x": 0.882, "y": 0.882 },
					{ "time": 0.8333, "x": 1.098, "y": 1.098 }
				]
			},
			"MAIN7": {
				"rotate": [
					{ "value": -133.95 },
					{ "time": 0.4, "value": 475.72 },
					{ "time": 0.4333, "value": -133.95 },
					{ "time": 0.8333, "value": 475.72 }
				],
				"scale": [
					{ "x": 0.882, "y": 0.882 },
					{ "time": 0.4, "x": 1.028, "y": 1.028 },
					{ "time": 0.4333, "x": 0.882, "y": 0.882 },
					{ "time": 0.8333, "x": 1.028, "y": 1.028 }
				]
			},
			"1_00": {
				"translate": [
					{ "y": 342 }
				],
				"scale": [
					{ "x": 1.017, "y": 1.017 }
				]
			},
			"2_00": {
				"translate": [
					{ "y": 348 }
				],
				"scale": [
					{ "x": 1.329, "y": 1.329 }
				]
			},
			"skill-1jiaodiqiliu_00045": {
				"scale": [
					{ "x": 1.348, "y": 1.348 }
				]
			}
		},
		"attachments": {
			"default": {
				"spin_slash/spin_splash_1": {
					"FX/spin/spin_splash_": {
						"sequence": [
							{ "mode": "loop", "delay": 0.0504 },
							{ "time": 0.4333, "mode": "loop" }
						]
					}
				},
				"spin_slash/spin_splash_2": {
					"FX/spin/dusk_": {
						"sequence": [
							{ "mode": "loop", "delay": 0.0401 },
							{ "time": 0.4333, "mode": "loop" }
						]
					}
				},
				"spin_slash/spin_splash_3": {
					"FX/spin/spark_": {
						"sequence": [
							{ "mode": "loop", "delay": 0.0801 },
							{ "time": 0.4333, "mode": "loop" }
						]
					}
				}
			}
		},
		"drawOrder": [
			{
				"time": 0.0667,
				"offsets": [
					{ "slot": "skill-1jiaodiqiliu_00045", "offset": 3 },
					{ "slot": "spin_slash/spin_splash_1", "offset": 0 }
				]
			},
			{
				"time": 0.1,
				"offsets": [
					{ "slot": "skill-1jiaodiqiliu_00045", "offset": 3 }
				]
			},
			{
				"time": 0.1333,
				"offsets": [
					{ "slot": "spin_slash/spin_splash_1", "offset": 1 }
				]
			},
			{ "time": 0.1667 },
			{
				"time": 0.2,
				"offsets": [
					{ "slot": "skill-1jiaodiqiliu_00045", "offset": 3 },
					{ "slot": "spin_slash/spin_splash_1", "offset": 0 }
				]
			},
			{
				"time": 0.2333,
				"offsets": [
					{ "slot": "spin_slash/spin_splash_1", "offset": 1 }
				]
			},
			{
				"time": 0.3333,
				"offsets": [
					{ "slot": "skill-1jiaodiqiliu_00045", "offset": 3 },
					{ "slot": "spin_slash/spin_splash_1", "offset": 0 }
				]
			},
			{ "time": 0.3667 },
			{
				"time": 0.5,
				"offsets": [
					{ "slot": "skill-1jiaodiqiliu_00045", "offset": 3 },
					{ "slot": "spin_slash/spin_splash_1", "offset": 0 }
				]
			},
			{
				"time": 0.5333,
				"offsets": [
					{ "slot": "skill-1jiaodiqiliu_00045", "offset": 3 }
				]
			},
			{
				"time": 0.5667,
				"offsets": [
					{ "slot": "spin_slash/spin_splash_1", "offset": 1 }
				]
			},
			{ "time": 0.6 },
			{
				"time": 0.6333,
				"offsets": [
					{ "slot": "skill-1jiaodiqiliu_00045", "offset": 3 },
					{ "slot": "spin_slash/spin_splash_1", "offset": 0 }
				]
			},
			{
				"time": 0.6667,
				"offsets": [
					{ "slot": "spin_slash/spin_splash_1", "offset": 1 }
				]
			},
			{
				"time": 0.7667,
				"offsets": [
					{ "slot": "skill-1jiaodiqiliu_00045", "offset": 3 },
					{ "slot": "spin_slash/spin_splash_1", "offset": 0 }
				]
			},
			{ "time": 0.8 }
		]
	}
}
}